chico/log.py
chico/sql.py
chico/thread.py
chico-1.0.0.dist-info/LICENSE
chico-1.0.0.dist-info/METADATA
chico-1.0.0.dist-info/WHEEL
chico-1.0.0.dist-info/top_level.txt
chico-1.0.0.dist-info/RECORD
